{
  "test": "This is a test entry",
  "MRFAEJ": {
    "healingRequestId": "MRFAEJ",
    "characterRequesting": "Alden",
    "village": "Vhintl",
    "heartsToHeal": 3,
    "paymentOffered": "Example payment description",
    "healerName": "Alden",
    "status": "pending"
  },
  "UD6CG0": {
    "healingRequestId": "UD6CG0",
    "characterRequesting": "Alden",
    "village": "Vhintl",
    "heartsToHeal": 3,
    "paymentOffered": "Example payment description",
    "healerName": "Alden",
    "status": "pending",
    "timestamp": 1733903487550
  },
  "XZPQOM": {
    "healingRequestId": "XZPQOM",
    "characterRequesting": "Alden",
    "village": "Vhintl",
    "heartsToHeal": 3,
    "paymentOffered": "Example payment description",
    "healerName": "Alden",
    "status": "pending",
    "timestamp": 1733903763473
  },
  "3NTUSR": {
    "healingRequestId": "3NTUSR",
    "characterRequesting": "Alden",
    "village": "Vhintl",
    "heartsToHeal": 3,
    "paymentOffered": "Example payment description",
    "healerName": "Pratyusha",
    "status": "pending",
    "timestamp": 1733903780662
  },
  "IFY2YP": {
    "healingRequestId": "IFY2YP",
    "characterRequesting": "Alden",
    "village": "Vhintl",
    "heartsToHeal": 3,
    "paymentOffered": "Example payment description",
    "healerName": "Pratyusha",
    "status": "pending",
    "timestamp": 1733903952112
  },
  "P3VCB2": {
    "healingRequestId": "P3VCB2",
    "characterRequesting": "Alden",
    "village": "Vhintl",
    "heartsToHeal": 3,
    "paymentOffered": "Example payment description",
    "healerName": "Pratyusha",
    "status": "pending",
    "timestamp": 1733904183753
  },
  "GHZZB0": {
    "healingRequestId": "GHZZB0",
    "characterRequesting": "Alden",
    "village": "Vhintl",
    "heartsToHeal": 3,
    "paymentOffered": "Example payment description",
    "healerName": "Alden",
    "status": "pending",
    "timestamp": 1733904194215
  },
  "JHI2A6": {
    "healingRequestId": "JHI2A6",
    "characterRequesting": "Alden",
    "village": "Vhintl",
    "heartsToHeal": 3,
    "paymentOffered": "Example payment description",
    "healerName": "Alden",
    "status": "pending",
    "timestamp": 1733904255301
  },
  "6CEB2G": {
    "healingRequestId": "6CEB2G",
    "characterRequesting": "Alden",
    "village": "Vhintl",
    "heartsToHeal": 3,
    "paymentOffered": "Example payment description",
    "healerName": "Alden",
    "status": "pending",
    "timestamp": 1733904302724
  },
  "DX56O4": {
    "healingRequestId": "DX56O4",
    "characterRequesting": "Alden",
    "village": "Vhintl",
    "heartsToHeal": 3,
    "paymentOffered": "Example payment description",
    "healerName": "Alden",
    "status": "pending",
    "timestamp": 1733904327227
  },
  "HTD7EP": {
    "healingRequestId": "HTD7EP",
    "characterRequesting": "Alden",
    "village": "Vhintl",
    "heartsToHeal": 3,
    "paymentOffered": "Example payment description",
    "healerName": "Pratyusha",
    "status": "pending",
    "timestamp": 1733904334887
  },
  "3I2IUJ": {
    "healingRequestId": "3I2IUJ",
    "characterRequesting": "Alden",
    "village": "Vhintl",
    "heartsToHeal": 3,
    "paymentOffered": "Example payment description",
    "healerName": "Pratyusha",
    "status": "pending",
    "timestamp": 1733904476254
  },
  "U6ZILF": {
    "healingRequestId": "U6ZILF",
    "characterRequesting": "Alden",
    "village": "Vhintl",
    "heartsToHeal": 3,
    "paymentOffered": "Example payment description",
    "healerName": "Alden",
    "status": "pending",
    "timestamp": 1733904483793
  },
  "SZZFQ3": {
    "healingRequestId": "SZZFQ3",
    "characterRequesting": "Alden",
    "village": "Vhintl",
    "heartsToHeal": 3,
    "paymentOffered": "Example payment description",
    "healerName": "Alden",
    "status": "pending",
    "timestamp": 1733904607264
  },
  "KLLUVW": {
    "healingRequestId": "KLLUVW",
    "characterRequesting": "Alden",
    "village": "Vhintl",
    "heartsToHeal": 3,
    "paymentOffered": "Example payment description",
    "healerName": null,
    "status": "pending",
    "timestamp": 1733904727543
  },
  "PFGUVH": {
    "healingRequestId": "PFGUVH",
    "characterRequesting": "Alden",
    "village": "Vhintl",
    "heartsToHeal": 3,
    "paymentOffered": "Example payment description",
    "healerName": "Pratyusha",
    "status": "pending",
    "timestamp": 1733904738765
  },
  "THVJJE": {
    "healingRequestId": "THVJJE",
    "characterRequesting": "Alden",
    "village": "Vhintl",
    "heartsToHeal": 3,
    "paymentOffered": "2 grains of sand",
    "healerName": null,
    "status": "pending",
    "timestamp": 1733904908475
  },
  "QFVRA6": {
    "healingRequestId": "QFVRA6",
    "characterRequesting": "Alden",
    "village": "Vhintl",
    "heartsToHeal": 3,
    "paymentOffered": "No payment specified",
    "status": "fulfilled",
    "timestamp": 1733905249190
  },
  "S6CJWP": {
    "healingRequestId": "S6CJWP",
    "characterRequesting": "Alden",
    "village": "Vhintl",
    "heartsToHeal": 3,
    "paymentOffered": "No payment specified",
    "status": "pending",
    "timestamp": 1733905365951
  },
  "1B5V5C": {
    "healingRequestId": "1B5V5C",
    "characterRequesting": "Bow",
    "village": "rudania",
    "heartsToHeal": 3,
    "paymentOffered": "monster claw",
    "healerName": "Pratyusha",
    "status": "fulfilled",
    "timestamp": 1733906139057
  },
  "USFFG4": {
    "healingRequestId": "USFFG4",
    "characterRequesting": "Bow",
    "village": "rudania",
    "heartsToHeal": 7,
    "paymentOffered": "No payment specified",
    "healerName": null,
    "status": "fulfilled",
    "timestamp": 1733906341910
  },
  "YP6OWF": {
    "healingRequestId": "YP6OWF",
    "characterRequesting": "Bow",
    "village": "rudania",
    "heartsToHeal": 7,
    "paymentOffered": "No payment specified",
    "healerName": null,
    "status": "fulfilled",
    "timestamp": 1733906411359
  },
  "K6B9LL": {
    "healingRequestId": "K6B9LL",
    "characterRequesting": "Bow",
    "village": "rudania",
    "heartsToHeal": 7,
    "paymentOffered": "No payment specified",
    "healerName": "Pratyusha",
    "status": "fulfilled",
    "timestamp": 1733906470918
  },
  "MNGAXU": {
    "healingRequestId": "MNGAXU",
    "characterRequesting": "Bow",
    "village": "rudania",
    "heartsToHeal": 7,
    "paymentOffered": "Monster Claw x1",
    "healerName": "Pratyusha",
    "status": "fulfilled",
    "timestamp": 1733906701648
  },
  "VEXOB4": {
    "healingRequestId": "VEXOB4",
    "characterRequesting": "Bow",
    "village": "rudania",
    "heartsToHeal": 7,
    "paymentOffered": "Monster Claw",
    "healerName": "Pratyusha",
    "status": "fulfilled",
    "timestamp": 1733906996788
  }
}